{
  "version": "1",
  "metadata": {
    "marimo_version": "0.19.10"
  },
  "cells": [
    {
      "id": "Hbol",
      "code_hash": "0ebc5acf17894f8284783d59c6042350",
      "outputs": [
        {
          "type": "data",
          "data": {
            "text/plain": ""
          }
        }
      ],
      "console": []
    },
    {
      "id": "MJUe",
      "code_hash": "4f3445dd88d8cf902005da10db4e488c",
      "outputs": [
        {
          "type": "data",
          "data": {
            "text/markdown": "<span class=\"markdown prose dark:prose-invert contents\"><h1 id=\"self-assessment-questionnaire-explorer\">\ud83d\udcca Self-Assessment Questionnaire Explorer</h1>\n<span class=\"paragraph\">Explore the self-assessment responses from your team project.\nStudents answered this questionnaire for <strong>each group</strong> they participated in.</span></span>"
          }
        }
      ],
      "console": []
    },
    {
      "id": "vblA",
      "code_hash": "5e010ce5c7b5e8ee51bab44d3535a291",
      "outputs": [
        {
          "type": "data",
          "data": {
            "text/plain": ""
          }
        }
      ],
      "console": []
    },
    {
      "id": "bkHC",
      "code_hash": "e234f869fe21bb367079c5f03c8d3f32",
      "outputs": [
        {
          "type": "data",
          "data": {
            "text/plain": ""
          }
        }
      ],
      "console": []
    },
    {
      "id": "lEQa",
      "code_hash": "94a6add49b033008d3cebbef36fa3ca3",
      "outputs": [
        {
          "type": "data",
          "data": {
            "text/markdown": "<span class=\"markdown prose dark:prose-invert contents\"><h2 id=\"overview\">\ud83d\udcc8 Overview</h2>\n<table>\n<thead>\n<tr>\n<th>Metric</th>\n<th>Value</th>\n</tr>\n</thead>\n<tbody>\n<tr>\n<td>Total Responses</td>\n<td><strong>51</strong></td>\n</tr>\n<tr>\n<td>Unique Students</td>\n<td><strong>22</strong></td>\n</tr>\n<tr>\n<td>Teams Covered</td>\n<td><strong>9</strong></td>\n</tr>\n<tr>\n<td>Avg Responses per Student</td>\n<td><strong>2.3</strong></td>\n</tr>\n</tbody>\n</table></span>"
          }
        }
      ],
      "console": []
    },
    {
      "id": "PKri",
      "code_hash": "63bd8434b8c35a10754d862747da8b9e",
      "outputs": [
        {
          "type": "data",
          "data": {
            "text/markdown": "<span class=\"markdown prose dark:prose-invert contents\"><span class=\"paragraph\">Use the tabs below to explore different aspects.</span></span>"
          }
        }
      ],
      "console": []
    },
    {
      "id": "Xref",
      "code_hash": "966c173246226a32effb1ec25b2d192d",
      "outputs": [
        {
          "type": "data",
          "data": {
            "text/html": "<marimo-ui-element object-id='Xref-0' random-id='0ebcf649-2a87-6e64-db6f-a8eab6af5e23'><marimo-tabs data-initial-value='&quot;&quot;' data-label='null' data-tabs='[&quot;&lt;span class=&#92;&quot;markdown prose dark:prose-invert contents&#92;&quot;&gt;&lt;span class=&#92;&quot;paragraph&#92;&quot;&gt;\ud83d\udc64 By Student&lt;/span&gt;&lt;/span&gt;&quot;,&quot;&lt;span class=&#92;&quot;markdown prose dark:prose-invert contents&#92;&quot;&gt;&lt;span class=&#92;&quot;paragraph&#92;&quot;&gt;\ud83d\udc65 By Team&lt;/span&gt;&lt;/span&gt;&quot;,&quot;&lt;span class=&#92;&quot;markdown prose dark:prose-invert contents&#92;&quot;&gt;&lt;span class=&#92;&quot;paragraph&#92;&quot;&gt;\ud83d\udcca Distributions&lt;/span&gt;&lt;/span&gt;&quot;]'><div data-kind='tab'><span class=\"markdown prose dark:prose-invert contents\"><span class=\"paragraph\">student</span></span></div><div data-kind='tab'><span class=\"markdown prose dark:prose-invert contents\"><span class=\"paragraph\">team</span></span></div><div data-kind='tab'><span class=\"markdown prose dark:prose-invert contents\"><span class=\"paragraph\">distribution</span></span></div></marimo-tabs></marimo-ui-element>"
          }
        }
      ],
      "console": []
    },
    {
      "id": "SFPL",
      "code_hash": "52eb0bac25576b8232d637ce8802b945",
      "outputs": [
        {
          "type": "data",
          "data": {
            "text/plain": ""
          }
        }
      ],
      "console": []
    },
    {
      "id": "BYtC",
      "code_hash": "da8053a3ea9a74c0a3e6d54e3ce1e4b2",
      "outputs": [
        {
          "type": "error",
          "ename": "ancestor-stopped",
          "evalue": "This cell wasn't run because an ancestor was stopped with `mo.stop`: ",
          "traceback": []
        }
      ],
      "console": []
    },
    {
      "id": "RGSE",
      "code_hash": "7dd160064d0dcae602c03eeec341a4d2",
      "outputs": [
        {
          "type": "data",
          "data": {
            "text/markdown": "<span class=\"markdown prose dark:prose-invert contents\"><h3 id=\"see-the-answers-of-that-student-for-each-group-they-participated-in\">See the answers of that student for each group they participated in.</h3></span>"
          }
        }
      ],
      "console": []
    },
    {
      "id": "Kclp",
      "code_hash": "a1de61c9e873a657c1183ac3898c95df",
      "outputs": [
        {
          "type": "error",
          "ename": "ancestor-stopped",
          "evalue": "This cell wasn't run because an ancestor was stopped with `mo.stop`: ",
          "traceback": []
        }
      ],
      "console": []
    },
    {
      "id": "emfo",
      "code_hash": "cffab1575b9fa4f332e71a4847c7bfcb",
      "outputs": [
        {
          "type": "error",
          "ename": "ancestor-stopped",
          "evalue": "This cell wasn't run because an ancestor was stopped with `mo.stop`: ",
          "traceback": []
        }
      ],
      "console": []
    },
    {
      "id": "Hstk",
      "code_hash": "1cea723cf0cc8122f837c6aae5296c5f",
      "outputs": [
        {
          "type": "data",
          "data": {
            "text/html": "<marimo-ui-element object-id='Hstk-0' random-id='8c531c1a-e37b-d471-4926-5e58fe47a4d3'><marimo-dropdown data-initial-value='[&quot;Constraints&quot;]' data-label='&quot;&lt;span class=&#92;&quot;markdown prose dark:prose-invert contents&#92;&quot;&gt;&lt;span class=&#92;&quot;paragraph&#92;&quot;&gt;Select a team&lt;/span&gt;&lt;/span&gt;&quot;' data-options='[&quot;Constraints&quot;,&quot;Data Crawling &amp; Matrix Creation&quot;,&quot;Data Documentation&quot;,&quot;Evaluation &amp; Baseline&quot;,&quot;Management&quot;,&quot;Presentation&quot;,&quot;Questionnaire&quot;,&quot;Research Literature &amp; Algorithm&quot;,&quot;Visualization&quot;]' data-allow-select-none='false' data-searchable='false' data-full-width='false'></marimo-dropdown></marimo-ui-element>"
          }
        }
      ],
      "console": []
    },
    {
      "id": "nWHF",
      "code_hash": "8295284f9d6803d95180752ee00368f0",
      "outputs": [
        {
          "type": "data",
          "data": {
            "text/html": "<div style='display: flex;flex: 1;flex-direction: column;justify-content: flex-start;align-items: normal;flex-wrap: nowrap;gap: 0.5rem'><span class=\"markdown prose dark:prose-invert contents\"><h2 id=\"team-data-documentation\">\ud83d\udc65 Team: Data Documentation</h2></span><marimo-ui-element object-id='nWHF-0' random-id='059cfc79-1565-f5d6-952f-10a18312f9d3'><marimo-checkbox data-initial-value='false' data-label='&quot;&lt;span class=&#92;&quot;markdown prose dark:prose-invert contents&#92;&quot;&gt;&lt;span class=&#92;&quot;paragraph&#92;&quot;&gt;Show individual scores&lt;/span&gt;&lt;/span&gt;&quot;' data-disabled='false'></marimo-checkbox></marimo-ui-element></div>"
          }
        }
      ],
      "console": []
    },
    {
      "id": "iLit",
      "code_hash": "9a76fb6356d7f8465a3a7fcbedcd7b50",
      "outputs": [
        {
          "type": "data",
          "data": {
            "text/markdown": "<span class=\"markdown prose dark:prose-invert contents\"><span class=\"paragraph\"><strong>Members (4):</strong> Luca Gemballa, Wanja Tolksdorf, Jannik Schneider, Ellaine Salvador</span>\n<h3 id=\"team-scores-1best-4lowest\">Team Scores (1=Best, 4=Lowest)</h3>\n<table>\n<thead>\n<tr>\n<th>Category</th>\n<th>Average</th>\n</tr>\n</thead>\n<tbody>\n<tr>\n<td>Contribution</td>\n<td><strong>1.00</strong></td>\n</tr>\n<tr>\n<td>Group Dynamics</td>\n<td><strong>1.00</strong></td>\n</tr>\n<tr>\n<td>Reflection</td>\n<td><strong>1.50</strong></td>\n</tr>\n<tr>\n<td><strong>Overall</strong></td>\n<td><strong>1.10</strong></td>\n</tr>\n</tbody>\n</table></span>"
          }
        }
      ],
      "console": []
    },
    {
      "id": "ZHCJ",
      "code_hash": "78d649cc40dbc93d9109e3f89e692cc0",
      "outputs": [
        {
          "type": "data",
          "data": {
            "text/markdown": "<span class=\"markdown prose dark:prose-invert contents\"><h3 id=\"time-span\">Time Span</h3>\n<span class=\"paragraph\"><strong>Team active period:</strong> 2025-10-21 \u2192 2026-02-04</span>\n<table>\n<thead>\n<tr>\n<th>Member</th>\n<th>Start</th>\n<th>End</th>\n<th>Active Days</th>\n</tr>\n</thead>\n<tbody>\n<tr>\n<td>Luca Gemballa</td>\n<td>2025-11-02</td>\n<td>2026-01-16</td>\n<td>75</td>\n</tr>\n<tr>\n<td>Wanja Tolksdorf</td>\n<td>2025-10-21</td>\n<td>2025-11-21</td>\n<td>31</td>\n</tr>\n<tr>\n<td>Jannik Schneider</td>\n<td>2025-10-21</td>\n<td>2026-01-13</td>\n<td>84</td>\n</tr>\n<tr>\n<td>Ellaine Salvador</td>\n<td>2025-10-28</td>\n<td>2026-02-04</td>\n<td>99</td>\n</tr>\n</tbody>\n</table></span>"
          }
        }
      ],
      "console": []
    },
    {
      "id": "ROlb",
      "code_hash": "fcecd03258ba538a862cfec3a2898409",
      "outputs": [
        {
          "type": "data",
          "data": {
            "text/html": "<marimo-ui-element object-id='ROlb-0' random-id='99893117-a443-32fd-8674-49371a2b737a'><marimo-multiselect data-initial-value='[&quot;How did your group decide on deadlines and divide tasks?&quot;]' data-label='&quot;&lt;span class=&#92;&quot;markdown prose dark:prose-invert contents&#92;&quot;&gt;&lt;span class=&#92;&quot;paragraph&#92;&quot;&gt;Select questions to display&lt;/span&gt;&lt;/span&gt;&quot;' data-options='[&quot;How did your group decide on deadlines and divide tasks?&quot;,&quot;Overall, how would you describe the task-division process?&quot;,&quot;When disagreements occurred, how were they handled?&quot;,&quot;Did working as a group improve the final outcome?&quot;,&quot;What should be continued?&quot;,&quot;What should the group stop doing?&quot;,&quot;What should the group start doing?&quot;]' data-full-width='false'></marimo-multiselect></marimo-ui-element>"
          }
        }
      ],
      "console": []
    },
    {
      "id": "qnkX",
      "code_hash": "b204a50019e07b8cce2a44b6c388f758",
      "outputs": [
        {
          "type": "data",
          "data": {
            "text/html": "<div style='display: flex;flex: 1;flex-direction: column;justify-content: flex-start;align-items: normal;flex-wrap: nowrap;gap: 0.5rem'><span class=\"markdown prose dark:prose-invert contents\"><span class=\"paragraph\"><strong>How did your group decide on deadlines and divide tasks?</strong></span>\n<table>\n<thead>\n<tr>\n<th>Member</th>\n<th>Answer</th>\n</tr>\n</thead>\n<tbody>\n<tr>\n<td>Luca Gemballa</td>\n<td>Tasks and deadlines were clearly defined and well managed.</td>\n</tr>\n<tr>\n<td>Wanja Tolksdorf</td>\n<td>Tasks and deadlines were planned but needed frequent adjustment.</td>\n</tr>\n<tr>\n<td>Jannik Schneider</td>\n<td>Tasks and deadlines were planned but needed frequent adjustment.</td>\n</tr>\n<tr>\n<td>Ellaine Salvador</td>\n<td>Tasks and deadlines were clearly defined and well managed.</td>\n</tr>\n</tbody>\n</table></span></div>"
          }
        }
      ],
      "console": []
    },
    {
      "id": "TqIu",
      "code_hash": "f68f2c3df7ef626c9d89c20a905eeb8b",
      "outputs": [
        {
          "type": "data",
          "data": {
            "text/plain": ""
          }
        }
      ],
      "console": []
    },
    {
      "id": "Vxnm",
      "code_hash": "667bf2559e48b7c25e468ef870554fc9",
      "outputs": [
        {
          "type": "error",
          "ename": "ancestor-stopped",
          "evalue": "This cell wasn't run because an ancestor was stopped with `mo.stop`: ",
          "traceback": []
        }
      ],
      "console": [
        {
          "type": "stream",
          "name": "stderr",
          "text": "\u001b[33m[W 260212 15:37:29 altair_transformer:79]\u001b(B\u001b[m Failed to convert data to arrow format, falling back to CSV: `Import pyarrow` failed.  Use pip or conda to install the pyarrow package.\n",
          "mimetype": "text/plain"
        }
      ]
    },
    {
      "id": "DnEU",
      "code_hash": "85e8e262e3cf43e9908d09486470c6f6",
      "outputs": [
        {
          "type": "data",
          "data": {
            "text/plain": ""
          }
        }
      ],
      "console": []
    },
    {
      "id": "ulZA",
      "code_hash": "baf866e40083c93fa00d56cc6a002f6d",
      "outputs": [
        {
          "type": "data",
          "data": {
            "text/plain": ""
          }
        }
      ],
      "console": []
    },
    {
      "id": "ecfG",
      "code_hash": "68b9570d1cc61651f3c23af1eca74fd2",
      "outputs": [
        {
          "type": "data",
          "data": {
            "text/plain": ""
          }
        }
      ],
      "console": []
    },
    {
      "id": "Pvdt",
      "code_hash": null,
      "outputs": [
        {
          "type": "data",
          "data": {
            "text/plain": ""
          }
        }
      ],
      "console": []
    },
    {
      "id": "ZBYS",
      "code_hash": "9e584bcdc1fdf1a11a2b4f0f1867f0a3",
      "outputs": [
        {
          "type": "data",
          "data": {
            "text/plain": ""
          }
        }
      ],
      "console": []
    },
    {
      "id": "aLJB",
      "code_hash": null,
      "outputs": [
        {
          "type": "data",
          "data": {
            "text/plain": ""
          }
        }
      ],
      "console": []
    }
  ]
}